<?xml version="1.0" encoding="utf-8"?>
<extension version="2.5" type="plugin" group="system" method="upgrade">
    <name>Inceptive Multiple Categories for K2 (system plugin)</name>
    <author>Inceptive Design Labs</author>
    <authorEmail>info@inceptive.gr</authorEmail>
    <authorUrl>www.inceptive.gr</authorUrl>
    <copyright>Copyright (c) 2006-2012 Inceptive GP. All rights reserved.</copyright>
    <creationDate>March 3, 2013</creationDate>
    <license>GNU/GPLv3 http://www.gnu.org/licenses/gpl-3.0.html</license>
    <version>1.1</version>
    <description>Inceptive Multiple Categories for K2 (system plugin)</description>
    <files>
        <file plugin="incptvk2multiplecategories">incptvk2multiplecategories.php</file>
    </files>
</extension>
